setup.py
andromeda/__init__.py
andromeda.egg-info/PKG-INFO
andromeda.egg-info/SOURCES.txt
andromeda.egg-info/dependency_links.txt
andromeda.egg-info/requires.txt
andromeda.egg-info/top_level.txt
andromeda/context/__init__.py
andromeda/endpoint/__init__.py
andromeda/exception/__init__.py
andromeda/parsers/__init__.py