Metadata-Version: 1.0
Name: andromeda
Version: 0.1.0
Summary: declarative, class-driven framework written around flask
Home-page: https://www.github.com/illberoy/andromeda
Author: Roy Sommer
Author-email: UNKNOWN
License: UNKNOWN
Platform: UNKNOWN
